nnsmith/__init__.py
nnsmith/_version.py
nnsmith/difftest.py
nnsmith/error.py
nnsmith/filter.py
nnsmith/gir.py
nnsmith/graph_gen.py
nnsmith/logging.py
nnsmith/macro.py
nnsmith/narrow_spec.py
nnsmith/util.py
nnsmith/abstract/__init__.py
nnsmith/abstract/arith.py
nnsmith/abstract/dtype.py
nnsmith/abstract/extension.py
nnsmith/abstract/op.py
nnsmith/abstract/tensor.py
nnsmith/backends/__init__.py
nnsmith/backends/factory.py
nnsmith/backends/onnxruntime.py
nnsmith/backends/tensorrt.py
nnsmith/backends/tflite.py
nnsmith/backends/torchjit.py
nnsmith/backends/tvm.py
nnsmith/backends/xla.py
nnsmith/cli/__init__.py
nnsmith/cli/dtype_test.py
nnsmith/cli/fuzz.py
nnsmith/cli/model_exec.py
nnsmith/cli/model_gen.py
nnsmith/config/__init__.py
nnsmith/config/main.yaml
nnsmith/config/hydra/job_logging/console.yaml
nnsmith/config/hydra/job_logging/file.yaml
nnsmith/materialize/__init__.py
nnsmith/materialize/onnx/__init__.py
nnsmith/materialize/tensorflow/__init__.py
nnsmith/materialize/tensorflow/dialect.py
nnsmith/materialize/tensorflow/forward.py
nnsmith/materialize/tensorflow/tfnet.py
nnsmith/materialize/torch/__init__.py
nnsmith/materialize/torch/dialect.py
nnsmith/materialize/torch/forward.py
nnsmith/materialize/torch/input_gen.py
nnsmith/materialize/torch/numeric.py
nnsmith/materialize/torch/proxy_grad.py
nnsmith/materialize/torch/symbolnet.py
nnsmith-0.1.0.dist-info/LICENSE
nnsmith-0.1.0.dist-info/METADATA
nnsmith-0.1.0.dist-info/WHEEL
nnsmith-0.1.0.dist-info/entry_points.txt
nnsmith-0.1.0.dist-info/top_level.txt
nnsmith-0.1.0.dist-info/RECORD
