Metadata-Version: 2.1
Name: nnsmith
Version: 0.1.0
Summary: "Automatic DNN generation for fuzzing and more."
Home-page: https://github.com/ise-uiuc/nnsmith
License: Apache-2.0
Platform: any
Requires-Python: >=3.6
License-File: LICENSE
Requires-Dist: z3-solver (>=4.11.0)
Requires-Dist: hydra-core (>=1.2.0)
Requires-Dist: hydra-colorlog (>=1.2.0)
Requires-Dist: multipledispatch (>=0.6.0)
Requires-Dist: appdirs (>=1.4.4)
Requires-Dist: numpy
Provides-Extra: onnx
Requires-Dist: torch ; extra == 'onnx'
Requires-Dist: onnx ; extra == 'onnx'
Provides-Extra: onnxruntime
Requires-Dist: onnxruntime ; extra == 'onnxruntime'
Requires-Dist: torch ; extra == 'onnxruntime'
Requires-Dist: onnx ; extra == 'onnxruntime'
Provides-Extra: tensorflow
Requires-Dist: tf-nightly ; extra == 'tensorflow'
Provides-Extra: torch
Requires-Dist: torch ; extra == 'torch'
Provides-Extra: tvm
Requires-Dist: apache-tvm ; extra == 'tvm'
Requires-Dist: torch ; extra == 'tvm'
Requires-Dist: onnx ; extra == 'tvm'
